notiondb/__init__.py
notiondb/api.py
notiondb/block.py
notiondb/block_parser.py
notiondb/consts.py
notiondb/database.py
notiondb/fields.py
notiondb/model.py
notiondb/query_set.py
notiondb-1.0.2.dist-info/LICENSE
notiondb-1.0.2.dist-info/METADATA
notiondb-1.0.2.dist-info/WHEEL
notiondb-1.0.2.dist-info/top_level.txt
notiondb-1.0.2.dist-info/RECORD
