Metadata-Version: 2.1
Name: notiondb
Version: 1.0.2
Summary: Python 3 tools for interacting with Notion API
Home-page: https://github.com/ngviethoang/notiondb
Author: Viet Hoang
Author-email: ngviethoang0212@gmail.com
License: UNKNOWN
Project-URL: Bug Tracker, https://github.com/ngviethoang/notiondb/issues
Platform: UNKNOWN
Classifier: Programming Language :: Python :: 3
Classifier: License :: OSI Approved :: MIT License
Classifier: Operating System :: OS Independent
Requires-Python: >=3.6
License-File: LICENSE
